odoo/addons/account_statement_import_online_paypal/README.rst
odoo/addons/account_statement_import_online_paypal/__init__.py
odoo/addons/account_statement_import_online_paypal/__manifest__.py
odoo/addons/account_statement_import_online_paypal/i18n/account_statement_import_online_paypal.pot
odoo/addons/account_statement_import_online_paypal/i18n/es.po
odoo/addons/account_statement_import_online_paypal/i18n/it.po
odoo/addons/account_statement_import_online_paypal/models/__init__.py
odoo/addons/account_statement_import_online_paypal/models/online_bank_statement_provider_paypal.py
odoo/addons/account_statement_import_online_paypal/readme/CONFIGURE.md
odoo/addons/account_statement_import_online_paypal/readme/CONTRIBUTORS.md
odoo/addons/account_statement_import_online_paypal/readme/DESCRIPTION.md
odoo/addons/account_statement_import_online_paypal/readme/ROADMAP.md
odoo/addons/account_statement_import_online_paypal/readme/USAGE.md
odoo/addons/account_statement_import_online_paypal/static/description/icon.png
odoo/addons/account_statement_import_online_paypal/static/description/index.html
odoo/addons/account_statement_import_online_paypal/tests/__init__.py
odoo/addons/account_statement_import_online_paypal/tests/test_account_statement_import_online_paypal.py
odoo/addons/account_statement_import_online_paypal/views/online_bank_statement_provider.xml
odoo_addon_account_statement_import_online_paypal-18.0.1.0.2.1.dist-info/METADATA
odoo_addon_account_statement_import_online_paypal-18.0.1.0.2.1.dist-info/WHEEL
odoo_addon_account_statement_import_online_paypal-18.0.1.0.2.1.dist-info/top_level.txt
odoo_addon_account_statement_import_online_paypal-18.0.1.0.2.1.dist-info/RECORD
